minirobots/__init__.py
minirobots/__main__.py
minirobots/turtle.py
minirobots-tutorial/Desplazamiento de la tortuga.ipynb
minirobots-tutorial/Detener la tortuga.ipynb
minirobots-tutorial/Extender la clase Turtle.ipynb
minirobots-tutorial/Index.ipynb
minirobots-tutorial/Jugar con los leds.ipynb
minirobots-tutorial/Múltiples tortugas.ipynb
minirobots-tutorial/Optimizar la comunicación con la tortuga.ipynb
minirobots-tutorial/Primeros pasos.ipynb
minirobots-tutorial/Subir y bajar el lápiz.ipynb
minirobots-tutorial/Tocar notas y hacer melodías.ipynb
minirobots-tutorial/canvas_adelante_atras.png
minirobots-tutorial/canvas_cuadrado.png
minirobots-tutorial/canvas_estrellas_al_azar.png
minirobots-tutorial/canvas_hexagono.png
minirobots-tutorial/canvas_inicio.png
minirobots-tutorial/canvas_linea_punteada.png
minirobots-tutorial/canvas_octogono.png
minirobots-tutorial/canvas_pentagono.png
minirobots-tutorial/canvas_triangulo.png
minirobots-tutorial/canvas_triangulo_lineas_punteadas.png
minirobots-tutorial/minirobots.py
minirobots-tutorial/notas_musicales.png
minirobots-tutorial/.jupyter/migrated
minirobots-tutorial/.jupyter/custom/custom.css
minirobots-tutorial/.jupyter/custom/custom.js
minirobots-tutorial/.jupyter/custom/favicon.ico
minirobots-tutorial/.jupyter/custom/logo.png
minirobots_turtle-0.2.9.data/scripts/minirobots-serial-monitor
minirobots_turtle-0.2.9.data/scripts/minirobots-shell
minirobots_turtle-0.2.9.data/scripts/minirobots-tutorial
minirobots_turtle-0.2.9.dist-info/LICENCE
minirobots_turtle-0.2.9.dist-info/METADATA
minirobots_turtle-0.2.9.dist-info/WHEEL
minirobots_turtle-0.2.9.dist-info/top_level.txt
minirobots_turtle-0.2.9.dist-info/RECORD
