Metadata-Version: 2.1
Name: minirobots-turtle
Version: 0.2.9
Summary: Python client for Minirobots Turtle Robot (includes Jupyter tutorial)
Home-page: https://minirobots.com.ar
Author: Leo Vidarte
Author-email: lvidarte@gmail.com
License: UNKNOWN
Platform: UNKNOWN
Classifier: Development Status :: 4 - Beta
Classifier: Intended Audience :: Education
Classifier: License :: OSI Approved :: GNU General Public License v3 (GPLv3)
Classifier: Operating System :: MacOS :: MacOS X
Classifier: Operating System :: POSIX :: Linux
Classifier: Programming Language :: Python :: 3
Classifier: Programming Language :: Python :: 3.6
Classifier: Topic :: Education
Requires-Python: >=3.6
Requires-Dist: ipython (==7.17.0)
Requires-Dist: jupyter (==1.0.0)
Requires-Dist: requests (==2.24.0)
Requires-Dist: serial
